easymlops/__init__.py
easymlops/core/__init__.py
easymlops/core/pipe_object.py
easymlops/core/pipeline_object.py
easymlops/nlp/__init__.py
easymlops/nlp/preprocessing.py
easymlops/nlp/representation.py
easymlops/nlp/similarity.py
easymlops/nlp/core/__init__.py
easymlops/nlp/core/pipe_object.py
easymlops/nlp/core/pipeline_object.py
easymlops/table/__init__.py
easymlops/table/classification.py
easymlops/table/decomposition.py
easymlops/table/encoding.py
easymlops/table/ensemble.py
easymlops/table/perfopt.py
easymlops/table/regression.py
easymlops/table/callback/__init__.py
easymlops/table/callback/check.py
easymlops/table/core/__init__.py
easymlops/table/core/pipe_object.py
easymlops/table/core/pipeline_object.py
easymlops/table/extend/__init__.py
easymlops/table/extend/normalization.py
easymlops/table/feature_selection/__init__.py
easymlops/table/feature_selection/embed.py
easymlops/table/feature_selection/filter.py
easymlops/table/preprocessing/__init__.py
easymlops/table/preprocessing/bivar_operation.py
easymlops/table/preprocessing/core.py
easymlops/table/preprocessing/onevar_operation.py
easymlops/table/storage/__init__.py
easymlops/table/storage/elasticsearch_storage.py
easymlops/table/storage/faiss_storage.py
easymlops/table/storage/hbase_storage.py
easymlops/table/storage/kafka_storage.py
easymlops/table/storage/local_storage.py
easymlops/table/utils/__init__.py
easymlops/table/utils/cpu_mem_detector.py
easymlops/table/utils/faster_lgbm_predictor_multiclass.py
easymlops/table/utils/faster_lgbm_predictor_single.py
easymlops/table/utils/pandas_utils.py
easymlops-0.1.3.dist-info/LICENSE
easymlops-0.1.3.dist-info/METADATA
easymlops-0.1.3.dist-info/WHEEL
easymlops-0.1.3.dist-info/top_level.txt
easymlops-0.1.3.dist-info/RECORD
