Metadata-Version: 2.1
Name: easymlops
Version: 0.1.3
Summary: MLOps Toolkit In Pipeline
Home-page: https://github.com/zhulei227/EasyMLOps
Author: zhulei227
License: Apache-2.0
Requires-Python: >=3.6
License-File: LICENSE
Requires-Dist: numpy (>=1.17)
Requires-Dist: tqdm
Requires-Dist: dask (>=0.17)
Requires-Dist: pandas (>=0.25)
Requires-Dist: scipy
Requires-Dist: scikit-learn (>=0.21)
